distlre/__init__.py
distlre/distlre.py
distlre/localexecutor.py
distlre/remoteexecutor.py
distlre-0.0.4.dist-info/METADATA
distlre-0.0.4.dist-info/RECORD
distlre-0.0.4.dist-info/WHEEL
distlre-0.0.4.dist-info/top_level.txt
