Metadata-Version: 2.1
Name: distlre
Version: 0.0.4
Summary: A Python package to distribute commands on remote hosts viaSSH and to execute them locally in parallel.
Home-page: https://github.com/csbence/DistLRE
Author: Bence Cserna
Author-email: UNKNOWN
License: UNKNOWN
Platform: UNKNOWN
Requires-Dist: paramiko
